orca_test/__init__.py
orca_test/orca_test.py
orca_test/tests/integration/__init__.py
orca_test/tests/integration/integration_orca_test.py
orca_test-0.1.dist-info/METADATA
orca_test-0.1.dist-info/RECORD
orca_test-0.1.dist-info/WHEEL
orca_test-0.1.dist-info/top_level.txt
