Metadata-Version: 2.1
Name: orca-test
Version: 0.1
Summary: Assertions for testing the characteristics of orca tables and columns
Home-page: https://github.com/urbansim/orca_test
Author: UrbanSim Inc.
Author-email: info@urbansim.com
License: UNKNOWN
Platform: UNKNOWN
Classifier: Programming Language :: Python :: 2
Classifier: Programming Language :: Python :: 2.7
Classifier: Programming Language :: Python :: 3
Classifier: Programming Language :: Python :: 3.5
Classifier: Programming Language :: Python :: 3.6
Requires-Dist: numpy (>=1.0)
Requires-Dist: pandas (>=0.12)
Requires-Dist: orca (>=1.3.0)
